test00000000000032/__init__.py
test00000000000032-0.0.1.dist-info/METADATA
test00000000000032-0.0.1.dist-info/WHEEL
test00000000000032-0.0.1.dist-info/top_level.txt
test00000000000032-0.0.1.dist-info/RECORD
