Metadata-Version: 2.4
Name: test00000000000032
Version: 0.0.1
Summary: Temporary test package for token verification
Requires-Python: >=3.7
